LICENSE
utinni/__init__.py
utinni_fork-0.5.2.dist-info/LICENSE
utinni_fork-0.5.2.dist-info/METADATA
utinni_fork-0.5.2.dist-info/WHEEL
utinni_fork-0.5.2.dist-info/RECORD
