Metadata-Version: 2.1
Name: utinni-fork
Version: 0.5.2
Summary: Async client library for Empire's RESTful API
Home-page: https://github.com/SadParad1se/Utinni
License: GPL-3.0-only
Author: Marcello Salvati
Author-email: byt3bl33d3r@pm.me
Requires-Python: >=3.8,<4.0
Classifier: Environment :: Console
Classifier: License :: OSI Approved :: GNU General Public License v3 (GPLv3)
Classifier: Programming Language :: Python :: 3
Classifier: Programming Language :: Python :: 3.8
Classifier: Programming Language :: Python :: 3.9
Classifier: Programming Language :: Python :: 3.10
Classifier: Programming Language :: Python :: 3.11
Classifier: Programming Language :: Python :: 3.12
Classifier: Topic :: Security
Requires-Dist: httpx (>=0.25.0,<0.26.0)
Project-URL: Repository, https://github.com/SadParad1se/Utinni
